{
  "animateLoading": true,
  "borderRadius": "{{appsmith.theme.borderRadius.appBorderRadius}}",
  "bottomRow": 5,
  "dynamicBindingPathList": [
    {
      "key": "truncateButtonColor"
    },
    {
      "key": "fontFamily"
    },
    {
      "key": "borderRadius"
    }
  ],
  "dynamicHeight": "AUTO_HEIGHT",
  "dynamicTriggerPathList": [],
  "fontFamily": "{{appsmith.theme.fontFamily.appFont}}",
  "fontSize": "0.875rem",
  "fontStyle": "",
  "isLoading": false,
  "isVisible": true,
  "key": "ajed50pis2",
  "leftColumn": 9,
  "maxDynamicHeight": 9000,
  "minDynamicHeight": 4,
  "minWidth": 450,
  "mobileBottomRow": 37,
  "mobileLeftColumn": 24,
  "mobileRightColumn": 40,
  "mobileTopRow": 33,
  "needsErrorInfo": false,
  "originalBottomRow": 5,
  "originalTopRow": 1,
  "overflow": "NONE",
  "parentColumnSpace": 5.9013671875,
  "parentId": "6etpxv36qw",
  "parentRowSpace": 10,
  "renderMode": "CANVAS",
  "responsiveBehavior": "fill",
  "rightColumn": 37,
  "shouldTruncate": false,
  "text": "Already have an account?",
  "textAlign": "CENTER",
  "textColor": "#71717a",
  "topRow": 1,
  "truncateButtonColor": "{{appsmith.theme.colors.primaryColor}}",
  "type": "TEXT_WIDGET",
  "version": 1,
  "widgetId": "ce0sc3pxx9",
  "widgetName": "Text3Copy"
}